{
    "age": 1,
    "v": 20230124,
    "ll": {
        "Ashburn": [38.7911,-77.5264],
        "Frankfurt": [50.0812,8.6411],
        "Los Angeles":[34.0515,-118.2707],
        "Miami":[25.7806,-80.1826],
        "New York City": [40.7876,-74.06],
        "Amsterdam": [52.352,4.9392],
        "Milan": [45.4722,9.1922],
        "Moscow": [55.7483,37.6171],
        "Chișinău": [47.0188,28.8128],
        "Tokyo": [35.6289, 139.7915],
        "São Paulo": [-23.5335,-46.6359],
        "Bucharest": [44.4152,26.166],
        "Mumbai": [19.0748,72.8856],
        "Johannesburg": [-26.3811,27.8376],
        "Chicago": [41.8486,-87.6288],
        "Tel Aviv": [32.0666,34.7652],
        "London": [51.5164,-0.093],
        "Phoenix": [33.4532,-112.0748]
    },
    "cfgs": {
        "vmess": {
            "a": {
                "u": "04621bae-ab36-11ec-b909-0242ac120002",
                "pt": 22324
            }
        },
        "ws": {
	        "a": {
                "domain": "gagafans.pics",
                "u":"03fcc618-b93d-6796-6aed-8a38c975d581",
                "pt": 443,
                "path": "/linkvws"
            },
            "geturline": {
                "domain": "geturline.online",
                "u":"03fcc618-b93d-6796-6aed-8a38c975d581",
                "pt": 443,
                "path": "/linkvws"
            },
            "elite": {
                "domain": "elitetransfer.online",
                "u":"03fcc618-b93d-6796-6aed-8a38c975d581",
                "pt": 443,
                "path": "/linkvws"
            },
            "find": {
                "domain": "findmybooks.site",
                "u":"03fcc618-b93d-6796-6aed-8a38c975d581",
                "pt": 443,
                "path": "/linkvws"
            },
	        "usecf": {
		        "cf": true,
                "domain": "gagafans.pics",
                "u":"03fcc618-b93d-6796-6aed-8a38c975d581",
                "pt": 443,
                "path": "/linkvws"
            }
        }
    },
    "ws2vmess": {
        "asn": [],
        "ipsFree": [],
        "ipsVip": [],
        "cfg": "a"
    },

    "l": [
        {
            "name": "Free",
            "isVip": false,
            "image": "global",
            "servers": [
            ],
            "ws": [
                {
                    "city":"Server-Gt",
                    "desc": "websocket",
                    "ip": "gagafans.pics"
                },
                {
                    "city":"geturline",
                    "cfg": "geturline",
                    "desc": "websocket",
                    "ip": "geturline.online"
                },
                {
                    "cfg": "find",
                    "city":"findmybooks",
                    "desc": "websocket",
                    "ip": "findmybooks.site"
                },
                {
                    "cfg": "elite",
                    "city":"elite",
                    "desc": "websocket",
                    "ip": "elitetransfer.online"
                }

            ],
           "ws2": [
                {
                    "mmver": ["1.3.3", ""],
                    "cfg": "usecf",
                    "city": "ServerGt-boost",
                    "desc": "fast proxy",
                    "ip": "gagafans.pics#cf"
                }
	   ]
	}
    ]
}

