{
    "age": 1,
    "ageM": 1,
    "v": 20230124,
    "cfgs": {
        "vmess": {
            "a": {
                "u": "04621bae-ab36-11ec-b909-0242ac120002",
                "pt": 22324
            }
        },
        "ws": {
	        "a": {
                "domain": "gianter.mom",
                "u":"03fcc618-b93d-6796-6aed-8a38c975d581",
                "pt": 443,
                "path": "/linkvws"
            },
            "b": {
                "domain": "gears9292.autos",
                "u":"03fcc618-b93d-6796-6aed-8a38c975d581",
                "pt": 443,
                "path": "/linkvws"
            },
	        "usecf": {
		        "cf": true,
                "domain": "gagafans.pics",
                "u":"03fcc618-b93d-6796-6aed-8a38c975d581",
                "pt": 443,
                "path": "/linkvws"
            }
        }
    },

    "l": [
        {
            "name": "Free",
            "isVip": false,
            "image": "global",
            "servers": [
            ],
            "ws2": [
                {
                    "cfg": "a",
                    "city":"Server-giant",
                    "desc": "new 2.15",
                    "ip": "gianter.mom"
                },
                {
                    "cfg": "b",
                    "city":"Server-gears",
                    "ip": "gears9292.autos"
                },
                {
                    "mmver": ["1.3.3", ""],
                    "cfg": "usecf",
                    "city": "ServerGt-boost",
                    "desc": "fast proxy",
                    "ip": "gagafans.pics#cf"
                }
            ]
        }
    ]
}

