{
    "ageM": 5,
    "v": 20241017,
    "shuffleWs": true,
    "cfgs": {
    },
    "l": [
        {
            "name": "Free",
            "isVip": false,
            "image": "global",
            "wsGroupSize": 1,
            "wsNameAuto": true,
            "ws2": [ ],
            "ws3": [
                { "name": "Server-1", "desc": "Global", "domain": "light3a.pro", "on": "12.3-0815" },
                { "name": "Server-2", "desc": "Global", "domain": "bl.light3a.pro"},
                { "name": "Server-3", "desc": "Global", "domain": "cl.light3a.pro"},

                { "name": "Server-1", "desc": "Global", "domain": "light3b.pro", "on": "12.3-0815" },
                { "name": "Server-2", "desc": "Global", "domain": "bl.light3b.pro"},
                { "name": "Server-3", "desc": "Global", "domain": "cl.light3b.pro"},
                   
                {"memo": "light"}
            ]
        }
    ]
}

